{
  "started_at": "2026-04-15 14:07:42",
  "cases": [
    {
      "case": {
        "case_id": "02_4",
        "busiType": "02_4",
        "entType": "4540",
        "rounds": 3
      },
      "round_runs": [
        {
          "target": "https://zhjg.scjdglj.gxzf.gov.cn:9087/icpsp-web-pc/name-register.html#/guide/base?busiType=02_4&entType=4540&marPrId=&marUniscId=",
          "logs": [
            {
              "before": {
                "href": "https://zhjg.scjdglj.gxzf.gov.cn:9087/icpsp-web-pc/name-register.html#/guide/base?busiType=02_4&entType=4540&marPrId=&marUniscId=",
                "hash": "#/guide/base?busiType=02_4&entType=4540&marPrId=&marUniscId=",
                "hasGuideBase": true,
                "hasCore": false,
                "hasYunbangban": false,
                "hasNamePrompt": false,
                "hasQualificationPrompt": false,
                "buttons": [
                  {
                    "text": "下一步",
                    "disabled": true
                  }
                ],
                "reqCount": 0
              },
              "actions": {
                "check_qualification": {
                  "clicked": 0,
                  "cbCount": 0,
                  "radioCount": 0
                },
                "close": false,
                "confirm": false,
                "select_not_apply": {
                  "ok": true,
                  "hit": "未申请",
                  "text": "广西数字政务一体化平台 标准版  国际版  首页  全部服务  **裕  用户信"
                },
                "next": false
              },
              "after": {
                "href": "https://zhjg.scjdglj.gxzf.gov.cn:9087/icpsp-web-pc/name-register.html#/guide/base?busiType=02_4&entType=4540&marPrId=&marUniscId=",
                "hash": "#/guide/base?busiType=02_4&entType=4540&marPrId=&marUniscId=",
                "hasGuideBase": true,
                "hasCore": false,
                "hasYunbangban": false,
                "hasNamePrompt": false,
                "hasQualificationPrompt": false,
                "buttons": [
                  {
                    "text": "下一步",
                    "disabled": true
                  }
                ],
                "reqCount": 0
              },
              "changed": false
            },
            {
              "before": {
                "href": "https://zhjg.scjdglj.gxzf.gov.cn:9087/icpsp-web-pc/name-register.html#/guide/base?busiType=02_4&entType=4540&marPrId=&marUniscId=",
                "hash": "#/guide/base?busiType=02_4&entType=4540&marPrId=&marUniscId=",
                "hasGuideBase": true,
                "hasCore": false,
                "hasYunbangban": false,
                "hasNamePrompt": false,
                "hasQualificationPrompt": false,
                "buttons": [
                  {
                    "text": "下一步",
                    "disabled": true
                  }
                ],
                "reqCount": 0
              },
              "actions": {
                "check_qualification": {
                  "clicked": 0,
                  "cbCount": 0,
                  "radioCount": 0
                },
                "close": false,
                "confirm": false,
                "select_not_apply": {
                  "ok": true,
                  "hit": "未申请",
                  "text": "广西数字政务一体化平台 标准版  国际版  首页  全部服务  **裕  用户信"
                },
                "next": false
              },
              "after": {
                "href": "https://zhjg.scjdglj.gxzf.gov.cn:9087/icpsp-web-pc/name-register.html#/guide/base?busiType=02_4&entType=4540&marPrId=&marUniscId=",
                "hash": "#/guide/base?busiType=02_4&entType=4540&marPrId=&marUniscId=",
                "hasGuideBase": true,
                "hasCore": false,
                "hasYunbangban": false,
                "hasNamePrompt": false,
                "hasQualificationPrompt": false,
                "buttons": [
                  {
                    "text": "下一步",
                    "disabled": true
                  }
                ],
                "reqCount": 0
              },
              "changed": false
            },
            {
              "before": {
                "href": "https://zhjg.scjdglj.gxzf.gov.cn:9087/icpsp-web-pc/name-register.html#/guide/base?busiType=02_4&entType=4540&marPrId=&marUniscId=",
                "hash": "#/guide/base?busiType=02_4&entType=4540&marPrId=&marUniscId=",
                "hasGuideBase": true,
                "hasCore": false,
                "hasYunbangban": false,
                "hasNamePrompt": false,
                "hasQualificationPrompt": false,
                "buttons": [
                  {
                    "text": "下一步",
                    "disabled": true
                  }
                ],
                "reqCount": 0
              },
              "actions": {
                "check_qualification": {
                  "clicked": 0,
                  "cbCount": 0,
                  "radioCount": 0
                },
                "close": false,
                "confirm": false,
                "select_not_apply": {
                  "ok": true,
                  "hit": "未申请",
                  "text": "广西数字政务一体化平台 标准版  国际版  首页  全部服务  **裕  用户信"
                },
                "next": false
              },
              "after": {
                "href": "https://zhjg.scjdglj.gxzf.gov.cn:9087/icpsp-web-pc/name-register.html#/guide/base?busiType=02_4&entType=4540&marPrId=&marUniscId=",
                "hash": "#/guide/base?busiType=02_4&entType=4540&marPrId=&marUniscId=",
                "hasGuideBase": true,
                "hasCore": false,
                "hasYunbangban": false,
                "hasNamePrompt": false,
                "hasQualificationPrompt": false,
                "buttons": [
                  {
                    "text": "下一步",
                    "disabled": true
                  }
                ],
                "reqCount": 0
              },
              "changed": false
            },
            {
              "before": {
                "href": "https://zhjg.scjdglj.gxzf.gov.cn:9087/icpsp-web-pc/name-register.html#/guide/base?busiType=02_4&entType=4540&marPrId=&marUniscId=",
                "hash": "#/guide/base?busiType=02_4&entType=4540&marPrId=&marUniscId=",
                "hasGuideBase": true,
                "hasCore": false,
                "hasYunbangban": false,
                "hasNamePrompt": false,
                "hasQualificationPrompt": false,
                "buttons": [
                  {
                    "text": "下一步",
                    "disabled": true
                  }
                ],
                "reqCount": 0
              },
              "actions": {
                "check_qualification": {
                  "clicked": 0,
                  "cbCount": 0,
                  "radioCount": 0
                },
                "close": false,
                "confirm": false,
                "select_not_apply": {
                  "ok": true,
                  "hit": "未申请",
                  "text": "广西数字政务一体化平台 标准版  国际版  首页  全部服务  **裕  用户信"
                },
                "next": false
              },
              "after": {
                "href": "https://zhjg.scjdglj.gxzf.gov.cn:9087/icpsp-web-pc/name-register.html#/guide/base?busiType=02_4&entType=4540&marPrId=&marUniscId=",
                "hash": "#/guide/base?busiType=02_4&entType=4540&marPrId=&marUniscId=",
                "hasGuideBase": true,
                "hasCore": false,
                "hasYunbangban": false,
                "hasNamePrompt": false,
                "hasQualificationPrompt": false,
                "buttons": [
                  {
                    "text": "下一步",
                    "disabled": true
                  }
                ],
                "reqCount": 0
              },
              "changed": false
            },
            {
              "before": {
                "href": "https://zhjg.scjdglj.gxzf.gov.cn:9087/icpsp-web-pc/name-register.html#/guide/base?busiType=02_4&entType=4540&marPrId=&marUniscId=",
                "hash": "#/guide/base?busiType=02_4&entType=4540&marPrId=&marUniscId=",
                "hasGuideBase": true,
                "hasCore": false,
                "hasYunbangban": false,
                "hasNamePrompt": false,
                "hasQualificationPrompt": false,
                "buttons": [
                  {
                    "text": "下一步",
                    "disabled": true
                  }
                ],
                "reqCount": 0
              },
              "actions": {
                "check_qualification": {
                  "clicked": 0,
                  "cbCount": 0,
                  "radioCount": 0
                },
                "close": false,
                "confirm": false,
                "select_not_apply": {
                  "ok": true,
                  "hit": "未申请",
                  "text": "广西数字政务一体化平台 标准版  国际版  首页  全部服务  **裕  用户信"
                },
                "next": false
              },
              "after": {
                "href": "https://zhjg.scjdglj.gxzf.gov.cn:9087/icpsp-web-pc/name-register.html#/guide/base?busiType=02_4&entType=4540&marPrId=&marUniscId=",
                "hash": "#/guide/base?busiType=02_4&entType=4540&marPrId=&marUniscId=",
                "hasGuideBase": true,
                "hasCore": false,
                "hasYunbangban": false,
                "hasNamePrompt": false,
                "hasQualificationPrompt": false,
                "buttons": [
                  {
                    "text": "下一步",
                    "disabled": true
                  }
                ],
                "reqCount": 0
              },
              "changed": false
            },
            {
              "before": {
                "href": "https://zhjg.scjdglj.gxzf.gov.cn:9087/icpsp-web-pc/name-register.html#/guide/base?busiType=02_4&entType=4540&marPrId=&marUniscId=",
                "hash": "#/guide/base?busiType=02_4&entType=4540&marPrId=&marUniscId=",
                "hasGuideBase": true,
                "hasCore": false,
                "hasYunbangban": false,
                "hasNamePrompt": false,
                "hasQualificationPrompt": false,
                "buttons": [
                  {
                    "text": "下一步",
                    "disabled": true
                  }
                ],
                "reqCount": 0
              },
              "actions": {
                "check_qualification": {
                  "clicked": 0,
                  "cbCount": 0,
                  "radioCount": 0
                },
                "close": false,
                "confirm": false,
                "select_not_apply": {
                  "ok": true,
                  "hit": "未申请",
                  "text": "广西数字政务一体化平台 标准版  国际版  首页  全部服务  **裕  用户信"
                },
                "next": false
              },
              "after": {
                "href": "https://zhjg.scjdglj.gxzf.gov.cn:9087/icpsp-web-pc/name-register.html#/guide/base?busiType=02_4&entType=4540&marPrId=&marUniscId=",
                "hash": "#/guide/base?busiType=02_4&entType=4540&marPrId=&marUniscId=",
                "hasGuideBase": true,
                "hasCore": false,
                "hasYunbangban": false,
                "hasNamePrompt": false,
                "hasQualificationPrompt": false,
                "buttons": [
                  {
                    "text": "下一步",
                    "disabled": true
                  }
                ],
                "reqCount": 0
              },
              "changed": false
            }
          ],
          "result": "blocked_no_side_effect",
          "final": {
            "href": "https://zhjg.scjdglj.gxzf.gov.cn:9087/icpsp-web-pc/name-register.html#/guide/base?busiType=02_4&entType=4540&marPrId=&marUniscId=",
            "hash": "#/guide/base?busiType=02_4&entType=4540&marPrId=&marUniscId=",
            "hasGuideBase": true,
            "hasCore": false,
            "hasYunbangban": false,
            "hasNamePrompt": false,
            "hasQualificationPrompt": false,
            "buttons": [
              {
                "text": "下一步",
                "disabled": true
              }
            ],
            "reqCount": 0
          }
        },
        {
          "target": "https://zhjg.scjdglj.gxzf.gov.cn:9087/icpsp-web-pc/name-register.html#/guide/base?busiType=02_4&entType=4540&marPrId=&marUniscId=",
          "logs": [
            {
              "before": {
                "href": "https://zhjg.scjdglj.gxzf.gov.cn:9087/icpsp-web-pc/name-register.html#/guide/base?busiType=02_4&entType=4540&marPrId=&marUniscId=",
                "hash": "#/guide/base?busiType=02_4&entType=4540&marPrId=&marUniscId=",
                "hasGuideBase": true,
                "hasCore": false,
                "hasYunbangban": false,
                "hasNamePrompt": false,
                "hasQualificationPrompt": false,
                "buttons": [
                  {
                    "text": "下一步",
                    "disabled": true
                  }
                ],
                "reqCount": 0
              },
              "actions": {
                "check_qualification": {
                  "clicked": 0,
                  "cbCount": 0,
                  "radioCount": 0
                },
                "close": false,
                "confirm": false,
                "select_not_apply": {
                  "ok": true,
                  "hit": "未申请",
                  "text": "广西数字政务一体化平台 标准版  国际版  首页  全部服务  **裕  用户信"
                },
                "next": false
              },
              "after": {
                "href": "https://zhjg.scjdglj.gxzf.gov.cn:9087/icpsp-web-pc/name-register.html#/guide/base?busiType=02_4&entType=4540&marPrId=&marUniscId=",
                "hash": "#/guide/base?busiType=02_4&entType=4540&marPrId=&marUniscId=",
                "hasGuideBase": true,
                "hasCore": false,
                "hasYunbangban": false,
                "hasNamePrompt": false,
                "hasQualificationPrompt": false,
                "buttons": [
                  {
                    "text": "下一步",
                    "disabled": true
                  }
                ],
                "reqCount": 0
              },
              "changed": false
            },
            {
              "before": {
                "href": "https://zhjg.scjdglj.gxzf.gov.cn:9087/icpsp-web-pc/name-register.html#/guide/base?busiType=02_4&entType=4540&marPrId=&marUniscId=",
                "hash": "#/guide/base?busiType=02_4&entType=4540&marPrId=&marUniscId=",
                "hasGuideBase": true,
                "hasCore": false,
                "hasYunbangban": false,
                "hasNamePrompt": false,
                "hasQualificationPrompt": false,
                "buttons": [
                  {
                    "text": "下一步",
                    "disabled": true
                  }
                ],
                "reqCount": 0
              },
              "actions": {
                "check_qualification": {
                  "clicked": 0,
                  "cbCount": 0,
                  "radioCount": 0
                },
                "close": false,
                "confirm": false,
                "select_not_apply": {
                  "ok": true,
                  "hit": "未申请",
                  "text": "广西数字政务一体化平台 标准版  国际版  首页  全部服务  **裕  用户信"
                },
                "next": false
              },
              "after": {
                "href": "https://zhjg.scjdglj.gxzf.gov.cn:9087/icpsp-web-pc/name-register.html#/guide/base?busiType=02_4&entType=4540&marPrId=&marUniscId=",
                "hash": "#/guide/base?busiType=02_4&entType=4540&marPrId=&marUniscId=",
                "hasGuideBase": true,
                "hasCore": false,
                "hasYunbangban": false,
                "hasNamePrompt": false,
                "hasQualificationPrompt": false,
                "buttons": [
                  {
                    "text": "下一步",
                    "disabled": true
                  }
                ],
                "reqCount": 0
              },
              "changed": false
            },
            {
              "before": {
                "href": "https://zhjg.scjdglj.gxzf.gov.cn:9087/icpsp-web-pc/name-register.html#/guide/base?busiType=02_4&entType=4540&marPrId=&marUniscId=",
                "hash": "#/guide/base?busiType=02_4&entType=4540&marPrId=&marUniscId=",
                "hasGuideBase": true,
                "hasCore": false,
                "hasYunbangban": false,
                "hasNamePrompt": false,
                "hasQualificationPrompt": false,
                "buttons": [
                  {
                    "text": "下一步",
                    "disabled": true
                  }
                ],
                "reqCount": 0
              },
              "actions": {
                "check_qualification": {
                  "clicked": 0,
                  "cbCount": 0,
                  "radioCount": 0
                },
                "close": false,
                "confirm": false,
                "select_not_apply": {
                  "ok": true,
                  "hit": "未申请",
                  "text": "广西数字政务一体化平台 标准版  国际版  首页  全部服务  **裕  用户信"
                },
                "next": false
              },
              "after": {
                "href": "https://zhjg.scjdglj.gxzf.gov.cn:9087/icpsp-web-pc/name-register.html#/guide/base?busiType=02_4&entType=4540&marPrId=&marUniscId=",
                "hash": "#/guide/base?busiType=02_4&entType=4540&marPrId=&marUniscId=",
                "hasGuideBase": true,
                "hasCore": false,
                "hasYunbangban": false,
                "hasNamePrompt": false,
                "hasQualificationPrompt": false,
                "buttons": [
                  {
                    "text": "下一步",
                    "disabled": true
                  }
                ],
                "reqCount": 0
              },
              "changed": false
            },
            {
              "before": {
                "href": "https://zhjg.scjdglj.gxzf.gov.cn:9087/icpsp-web-pc/name-register.html#/guide/base?busiType=02_4&entType=4540&marPrId=&marUniscId=",
                "hash": "#/guide/base?busiType=02_4&entType=4540&marPrId=&marUniscId=",
                "hasGuideBase": true,
                "hasCore": false,
                "hasYunbangban": false,
                "hasNamePrompt": false,
                "hasQualificationPrompt": false,
                "buttons": [
                  {
                    "text": "下一步",
                    "disabled": true
                  }
                ],
                "reqCount": 0
              },
              "actions": {
                "check_qualification": {
                  "clicked": 0,
                  "cbCount": 0,
                  "radioCount": 0
                },
                "close": false,
                "confirm": false,
                "select_not_apply": {
                  "ok": true,
                  "hit": "未申请",
                  "text": "广西数字政务一体化平台 标准版  国际版  首页  全部服务  **裕  用户信"
                },
                "next": false
              },
              "after": {
                "href": "https://zhjg.scjdglj.gxzf.gov.cn:9087/icpsp-web-pc/name-register.html#/guide/base?busiType=02_4&entType=4540&marPrId=&marUniscId=",
                "hash": "#/guide/base?busiType=02_4&entType=4540&marPrId=&marUniscId=",
                "hasGuideBase": true,
                "hasCore": false,
                "hasYunbangban": false,
                "hasNamePrompt": false,
                "hasQualificationPrompt": false,
                "buttons": [
                  {
                    "text": "下一步",
                    "disabled": true
                  }
                ],
                "reqCount": 0
              },
              "changed": false
            },
            {
              "before": {
                "href": "https://zhjg.scjdglj.gxzf.gov.cn:9087/icpsp-web-pc/name-register.html#/guide/base?busiType=02_4&entType=4540&marPrId=&marUniscId=",
                "hash": "#/guide/base?busiType=02_4&entType=4540&marPrId=&marUniscId=",
                "hasGuideBase": true,
                "hasCore": false,
                "hasYunbangban": false,
                "hasNamePrompt": false,
                "hasQualificationPrompt": false,
                "buttons": [
                  {
                    "text": "下一步",
                    "disabled": true
                  }
                ],
                "reqCount": 0
              },
              "actions": {
                "check_qualification": {
                  "clicked": 0,
                  "cbCount": 0,
                  "radioCount": 0
                },
                "close": false,
                "confirm": false,
                "select_not_apply": {
                  "ok": true,
                  "hit": "未申请",
                  "text": "广西数字政务一体化平台 标准版  国际版  首页  全部服务  **裕  用户信"
                },
                "next": false
              },
              "after": {
                "href": "https://zhjg.scjdglj.gxzf.gov.cn:9087/icpsp-web-pc/name-register.html#/guide/base?busiType=02_4&entType=4540&marPrId=&marUniscId=",
                "hash": "#/guide/base?busiType=02_4&entType=4540&marPrId=&marUniscId=",
                "hasGuideBase": true,
                "hasCore": false,
                "hasYunbangban": false,
                "hasNamePrompt": false,
                "hasQualificationPrompt": false,
                "buttons": [
                  {
                    "text": "下一步",
                    "disabled": true
                  }
                ],
                "reqCount": 0
              },
              "changed": false
            },
            {
              "before": {
                "href": "https://zhjg.scjdglj.gxzf.gov.cn:9087/icpsp-web-pc/name-register.html#/guide/base?busiType=02_4&entType=4540&marPrId=&marUniscId=",
                "hash": "#/guide/base?busiType=02_4&entType=4540&marPrId=&marUniscId=",
                "hasGuideBase": true,
                "hasCore": false,
                "hasYunbangban": false,
                "hasNamePrompt": false,
                "hasQualificationPrompt": false,
                "buttons": [
                  {
                    "text": "下一步",
                    "disabled": true
                  }
                ],
                "reqCount": 0
              },
              "actions": {
                "check_qualification": {
                  "clicked": 0,
                  "cbCount": 0,
                  "radioCount": 0
                },
                "close": false,
                "confirm": false,
                "select_not_apply": {
                  "ok": true,
                  "hit": "未申请",
                  "text": "广西数字政务一体化平台 标准版  国际版  首页  全部服务  **裕  用户信"
                },
                "next": false
              },
              "after": {
                "href": "https://zhjg.scjdglj.gxzf.gov.cn:9087/icpsp-web-pc/name-register.html#/guide/base?busiType=02_4&entType=4540&marPrId=&marUniscId=",
                "hash": "#/guide/base?busiType=02_4&entType=4540&marPrId=&marUniscId=",
                "hasGuideBase": true,
                "hasCore": false,
                "hasYunbangban": false,
                "hasNamePrompt": false,
                "hasQualificationPrompt": false,
                "buttons": [
                  {
                    "text": "下一步",
                    "disabled": true
                  }
                ],
                "reqCount": 0
              },
              "changed": false
            }
          ],
          "result": "blocked_no_side_effect",
          "final": {
            "href": "https://zhjg.scjdglj.gxzf.gov.cn:9087/icpsp-web-pc/name-register.html#/guide/base?busiType=02_4&entType=4540&marPrId=&marUniscId=",
            "hash": "#/guide/base?busiType=02_4&entType=4540&marPrId=&marUniscId=",
            "hasGuideBase": true,
            "hasCore": false,
            "hasYunbangban": false,
            "hasNamePrompt": false,
            "hasQualificationPrompt": false,
            "buttons": [
              {
                "text": "下一步",
                "disabled": true
              }
            ],
            "reqCount": 0
          }
        },
        {
          "target": "https://zhjg.scjdglj.gxzf.gov.cn:9087/icpsp-web-pc/name-register.html#/guide/base?busiType=02_4&entType=4540&marPrId=&marUniscId=",
          "logs": [
            {
              "before": {
                "href": "https://zhjg.scjdglj.gxzf.gov.cn:9087/icpsp-web-pc/name-register.html#/guide/base?busiType=02_4&entType=4540&marPrId=&marUniscId=",
                "hash": "#/guide/base?busiType=02_4&entType=4540&marPrId=&marUniscId=",
                "hasGuideBase": true,
                "hasCore": false,
                "hasYunbangban": false,
                "hasNamePrompt": false,
                "hasQualificationPrompt": false,
                "buttons": [
                  {
                    "text": "下一步",
                    "disabled": true
                  }
                ],
                "reqCount": 0
              },
              "actions": {
                "check_qualification": {
                  "clicked": 0,
                  "cbCount": 0,
                  "radioCount": 0
                },
                "close": false,
                "confirm": false,
                "select_not_apply": {
                  "ok": true,
                  "hit": "未申请",
                  "text": "广西数字政务一体化平台 标准版  国际版  首页  全部服务  **裕  用户信"
                },
                "next": false
              },
              "after": {
                "href": "https://zhjg.scjdglj.gxzf.gov.cn:9087/icpsp-web-pc/name-register.html#/guide/base?busiType=02_4&entType=4540&marPrId=&marUniscId=",
                "hash": "#/guide/base?busiType=02_4&entType=4540&marPrId=&marUniscId=",
                "hasGuideBase": true,
                "hasCore": false,
                "hasYunbangban": false,
                "hasNamePrompt": false,
                "hasQualificationPrompt": false,
                "buttons": [
                  {
                    "text": "下一步",
                    "disabled": true
                  }
                ],
                "reqCount": 0
              },
              "changed": false
            },
            {
              "before": {
                "href": "https://zhjg.scjdglj.gxzf.gov.cn:9087/icpsp-web-pc/name-register.html#/guide/base?busiType=02_4&entType=4540&marPrId=&marUniscId=",
                "hash": "#/guide/base?busiType=02_4&entType=4540&marPrId=&marUniscId=",
                "hasGuideBase": true,
                "hasCore": false,
                "hasYunbangban": false,
                "hasNamePrompt": false,
                "hasQualificationPrompt": false,
                "buttons": [
                  {
                    "text": "下一步",
                    "disabled": true
                  }
                ],
                "reqCount": 0
              },
              "actions": {
                "check_qualification": {
                  "clicked": 0,
                  "cbCount": 0,
                  "radioCount": 0
                },
                "close": false,
                "confirm": false,
                "select_not_apply": {
                  "ok": true,
                  "hit": "未申请",
                  "text": "广西数字政务一体化平台 标准版  国际版  首页  全部服务  **裕  用户信"
                },
                "next": false
              },
              "after": {
                "href": "https://zhjg.scjdglj.gxzf.gov.cn:9087/icpsp-web-pc/name-register.html#/guide/base?busiType=02_4&entType=4540&marPrId=&marUniscId=",
                "hash": "#/guide/base?busiType=02_4&entType=4540&marPrId=&marUniscId=",
                "hasGuideBase": true,
                "hasCore": false,
                "hasYunbangban": false,
                "hasNamePrompt": false,
                "hasQualificationPrompt": false,
                "buttons": [
                  {
                    "text": "下一步",
                    "disabled": true
                  }
                ],
                "reqCount": 0
              },
              "changed": false
            },
            {
              "before": {
                "href": "https://zhjg.scjdglj.gxzf.gov.cn:9087/icpsp-web-pc/name-register.html#/guide/base?busiType=02_4&entType=4540&marPrId=&marUniscId=",
                "hash": "#/guide/base?busiType=02_4&entType=4540&marPrId=&marUniscId=",
                "hasGuideBase": true,
                "hasCore": false,
                "hasYunbangban": false,
                "hasNamePrompt": false,
                "hasQualificationPrompt": false,
                "buttons": [
                  {
                    "text": "下一步",
                    "disabled": true
                  }
                ],
                "reqCount": 0
              },
              "actions": {
                "check_qualification": {
                  "clicked": 0,
                  "cbCount": 0,
                  "radioCount": 0
                },
                "close": false,
                "confirm": false,
                "select_not_apply": {
                  "ok": true,
                  "hit": "未申请",
                  "text": "广西数字政务一体化平台 标准版  国际版  首页  全部服务  **裕  用户信"
                },
                "next": false
              },
              "after": {
                "href": "https://zhjg.scjdglj.gxzf.gov.cn:9087/icpsp-web-pc/name-register.html#/guide/base?busiType=02_4&entType=4540&marPrId=&marUniscId=",
                "hash": "#/guide/base?busiType=02_4&entType=4540&marPrId=&marUniscId=",
                "hasGuideBase": true,
                "hasCore": false,
                "hasYunbangban": false,
                "hasNamePrompt": false,
                "hasQualificationPrompt": false,
                "buttons": [
                  {
                    "text": "下一步",
                    "disabled": true
                  }
                ],
                "reqCount": 0
              },
              "changed": false
            },
            {
              "before": {
                "href": "https://zhjg.scjdglj.gxzf.gov.cn:9087/icpsp-web-pc/name-register.html#/guide/base?busiType=02_4&entType=4540&marPrId=&marUniscId=",
                "hash": "#/guide/base?busiType=02_4&entType=4540&marPrId=&marUniscId=",
                "hasGuideBase": true,
                "hasCore": false,
                "hasYunbangban": false,
                "hasNamePrompt": false,
                "hasQualificationPrompt": false,
                "buttons": [
                  {
                    "text": "下一步",
                    "disabled": true
                  }
                ],
                "reqCount": 0
              },
              "actions": {
                "check_qualification": {
                  "clicked": 0,
                  "cbCount": 0,
                  "radioCount": 0
                },
                "close": false,
                "confirm": false,
                "select_not_apply": {
                  "ok": true,
                  "hit": "未申请",
                  "text": "广西数字政务一体化平台 标准版  国际版  首页  全部服务  **裕  用户信"
                },
                "next": false
              },
              "after": {
                "href": "https://zhjg.scjdglj.gxzf.gov.cn:9087/icpsp-web-pc/name-register.html#/guide/base?busiType=02_4&entType=4540&marPrId=&marUniscId=",
                "hash": "#/guide/base?busiType=02_4&entType=4540&marPrId=&marUniscId=",
                "hasGuideBase": true,
                "hasCore": false,
                "hasYunbangban": false,
                "hasNamePrompt": false,
                "hasQualificationPrompt": false,
                "buttons": [
                  {
                    "text": "下一步",
                    "disabled": true
                  }
                ],
                "reqCount": 0
              },
              "changed": false
            },
            {
              "before": {
                "href": "https://zhjg.scjdglj.gxzf.gov.cn:9087/icpsp-web-pc/name-register.html#/guide/base?busiType=02_4&entType=4540&marPrId=&marUniscId=",
                "hash": "#/guide/base?busiType=02_4&entType=4540&marPrId=&marUniscId=",
                "hasGuideBase": true,
                "hasCore": false,
                "hasYunbangban": false,
                "hasNamePrompt": false,
                "hasQualificationPrompt": false,
                "buttons": [
                  {
                    "text": "下一步",
                    "disabled": true
                  }
                ],
                "reqCount": 0
              },
              "actions": {
                "check_qualification": {
                  "clicked": 0,
                  "cbCount": 0,
                  "radioCount": 0
                },
                "close": false,
                "confirm": false,
                "select_not_apply": {
                  "ok": true,
                  "hit": "未申请",
                  "text": "广西数字政务一体化平台 标准版  国际版  首页  全部服务  **裕  用户信"
                },
                "next": false
              },
              "after": {
                "href": "https://zhjg.scjdglj.gxzf.gov.cn:9087/icpsp-web-pc/name-register.html#/guide/base?busiType=02_4&entType=4540&marPrId=&marUniscId=",
                "hash": "#/guide/base?busiType=02_4&entType=4540&marPrId=&marUniscId=",
                "hasGuideBase": true,
                "hasCore": false,
                "hasYunbangban": false,
                "hasNamePrompt": false,
                "hasQualificationPrompt": false,
                "buttons": [
                  {
                    "text": "下一步",
                    "disabled": true
                  }
                ],
                "reqCount": 0
              },
              "changed": false
            },
            {
              "before": {
                "href": "https://zhjg.scjdglj.gxzf.gov.cn:9087/icpsp-web-pc/name-register.html#/guide/base?busiType=02_4&entType=4540&marPrId=&marUniscId=",
                "hash": "#/guide/base?busiType=02_4&entType=4540&marPrId=&marUniscId=",
                "hasGuideBase": true,
                "hasCore": false,
                "hasYunbangban": false,
                "hasNamePrompt": false,
                "hasQualificationPrompt": false,
                "buttons": [
                  {
                    "text": "下一步",
                    "disabled": true
                  }
                ],
                "reqCount": 0
              },
              "actions": {
                "check_qualification": {
                  "clicked": 0,
                  "cbCount": 0,
                  "radioCount": 0
                },
                "close": false,
                "confirm": false,
                "select_not_apply": {
                  "ok": true,
                  "hit": "未申请",
                  "text": "广西数字政务一体化平台 标准版  国际版  首页  全部服务  **裕  用户信"
                },
                "next": false
              },
              "after": {
                "href": "https://zhjg.scjdglj.gxzf.gov.cn:9087/icpsp-web-pc/name-register.html#/guide/base?busiType=02_4&entType=4540&marPrId=&marUniscId=",
                "hash": "#/guide/base?busiType=02_4&entType=4540&marPrId=&marUniscId=",
                "hasGuideBase": true,
                "hasCore": false,
                "hasYunbangban": false,
                "hasNamePrompt": false,
                "hasQualificationPrompt": false,
                "buttons": [
                  {
                    "text": "下一步",
                    "disabled": true
                  }
                ],
                "reqCount": 0
              },
              "changed": false
            }
          ],
          "result": "blocked_no_side_effect",
          "final": {
            "href": "https://zhjg.scjdglj.gxzf.gov.cn:9087/icpsp-web-pc/name-register.html#/guide/base?busiType=02_4&entType=4540&marPrId=&marUniscId=",
            "hash": "#/guide/base?busiType=02_4&entType=4540&marPrId=&marUniscId=",
            "hasGuideBase": true,
            "hasCore": false,
            "hasYunbangban": false,
            "hasNamePrompt": false,
            "hasQualificationPrompt": false,
            "buttons": [
              {
                "text": "下一步",
                "disabled": true
              }
            ],
            "reqCount": 0
          }
        }
      ],
      "summary": {
        "any_transition": false,
        "all_blocked": true
      }
    },
    {
      "case": {
        "case_id": "07",
        "busiType": "07",
        "entType": "1100",
        "rounds": 2
      },
      "round_runs": [
        {
          "target": "https://zhjg.scjdglj.gxzf.gov.cn:9087/icpsp-web-pc/name-register.html#/guide/base?busiType=07&entType=1100&marPrId=&marUniscId=",
          "logs": [
            {
              "before": {
                "href": "https://zhjg.scjdglj.gxzf.gov.cn:9087/icpsp-web-pc/name-register.html#/guide/base?busiType=07&entType=1100&marPrId=&marUniscId=",
                "hash": "#/guide/base?busiType=07&entType=1100&marPrId=&marUniscId=",
                "hasGuideBase": true,
                "hasCore": false,
                "hasYunbangban": false,
                "hasNamePrompt": false,
                "hasQualificationPrompt": false,
                "buttons": [
                  {
                    "text": "下一步",
                    "disabled": true
                  }
                ],
                "reqCount": 0
              },
              "actions": {
                "check_qualification": {
                  "clicked": 0,
                  "cbCount": 0,
                  "radioCount": 0
                },
                "close": false,
                "confirm": false,
                "select_not_apply": {
                  "ok": true,
                  "hit": "未申请",
                  "text": "广西数字政务一体化平台 标准版  国际版  首页  全部服务  **裕  用户信"
                },
                "next": false
              },
              "after": {
                "href": "https://zhjg.scjdglj.gxzf.gov.cn:9087/icpsp-web-pc/name-register.html#/guide/base?busiType=07&entType=1100&marPrId=&marUniscId=",
                "hash": "#/guide/base?busiType=07&entType=1100&marPrId=&marUniscId=",
                "hasGuideBase": true,
                "hasCore": false,
                "hasYunbangban": false,
                "hasNamePrompt": false,
                "hasQualificationPrompt": false,
                "buttons": [
                  {
                    "text": "下一步",
                    "disabled": true
                  }
                ],
                "reqCount": 0
              },
              "changed": false
            },
            {
              "before": {
                "href": "https://zhjg.scjdglj.gxzf.gov.cn:9087/icpsp-web-pc/name-register.html#/guide/base?busiType=07&entType=1100&marPrId=&marUniscId=",
                "hash": "#/guide/base?busiType=07&entType=1100&marPrId=&marUniscId=",
                "hasGuideBase": true,
                "hasCore": false,
                "hasYunbangban": false,
                "hasNamePrompt": false,
                "hasQualificationPrompt": false,
                "buttons": [
                  {
                    "text": "下一步",
                    "disabled": true
                  }
                ],
                "reqCount": 0
              },
              "actions": {
                "check_qualification": {
                  "clicked": 0,
                  "cbCount": 0,
                  "radioCount": 0
                },
                "close": false,
                "confirm": false,
                "select_not_apply": {
                  "ok": true,
                  "hit": "未申请",
                  "text": "广西数字政务一体化平台 标准版  国际版  首页  全部服务  **裕  用户信"
                },
                "next": false
              },
              "after": {
                "href": "https://zhjg.scjdglj.gxzf.gov.cn:9087/icpsp-web-pc/name-register.html#/guide/base?busiType=07&entType=1100&marPrId=&marUniscId=",
                "hash": "#/guide/base?busiType=07&entType=1100&marPrId=&marUniscId=",
                "hasGuideBase": true,
                "hasCore": false,
                "hasYunbangban": false,
                "hasNamePrompt": false,
                "hasQualificationPrompt": false,
                "buttons": [
                  {
                    "text": "下一步",
                    "disabled": true
                  }
                ],
                "reqCount": 0
              },
              "changed": false
            },
            {
              "before": {
                "href": "https://zhjg.scjdglj.gxzf.gov.cn:9087/icpsp-web-pc/name-register.html#/guide/base?busiType=07&entType=1100&marPrId=&marUniscId=",
                "hash": "#/guide/base?busiType=07&entType=1100&marPrId=&marUniscId=",
                "hasGuideBase": true,
                "hasCore": false,
                "hasYunbangban": false,
                "hasNamePrompt": false,
                "hasQualificationPrompt": false,
                "buttons": [
                  {
                    "text": "下一步",
                    "disabled": true
                  }
                ],
                "reqCount": 0
              },
              "actions": {
                "check_qualification": {
                  "clicked": 0,
                  "cbCount": 0,
                  "radioCount": 0
                },
                "close": false,
                "confirm": false,
                "select_not_apply": {
                  "ok": true,
                  "hit": "未申请",
                  "text": "广西数字政务一体化平台 标准版  国际版  首页  全部服务  **裕  用户信"
                },
                "next": false
              },
              "after": {
                "href": "https://zhjg.scjdglj.gxzf.gov.cn:9087/icpsp-web-pc/name-register.html#/guide/base?busiType=07&entType=1100&marPrId=&marUniscId=",
                "hash": "#/guide/base?busiType=07&entType=1100&marPrId=&marUniscId=",
                "hasGuideBase": true,
                "hasCore": false,
                "hasYunbangban": false,
                "hasNamePrompt": false,
                "hasQualificationPrompt": false,
                "buttons": [
                  {
                    "text": "下一步",
                    "disabled": true
                  }
                ],
                "reqCount": 0
              },
              "changed": false
            },
            {
              "before": {
                "href": "https://zhjg.scjdglj.gxzf.gov.cn:9087/icpsp-web-pc/name-register.html#/guide/base?busiType=07&entType=1100&marPrId=&marUniscId=",
                "hash": "#/guide/base?busiType=07&entType=1100&marPrId=&marUniscId=",
                "hasGuideBase": true,
                "hasCore": false,
                "hasYunbangban": false,
                "hasNamePrompt": false,
                "hasQualificationPrompt": false,
                "buttons": [
                  {
                    "text": "下一步",
                    "disabled": true
                  }
                ],
                "reqCount": 0
              },
              "actions": {
                "check_qualification": {
                  "clicked": 0,
                  "cbCount": 0,
                  "radioCount": 0
                },
                "close": false,
                "confirm": false,
                "select_not_apply": {
                  "ok": true,
                  "hit": "未申请",
                  "text": "广西数字政务一体化平台 标准版  国际版  首页  全部服务  **裕  用户信"
                },
                "next": false
              },
              "after": {
                "href": "https://zhjg.scjdglj.gxzf.gov.cn:9087/icpsp-web-pc/name-register.html#/guide/base?busiType=07&entType=1100&marPrId=&marUniscId=",
                "hash": "#/guide/base?busiType=07&entType=1100&marPrId=&marUniscId=",
                "hasGuideBase": true,
                "hasCore": false,
                "hasYunbangban": false,
                "hasNamePrompt": false,
                "hasQualificationPrompt": false,
                "buttons": [
                  {
                    "text": "下一步",
                    "disabled": true
                  }
                ],
                "reqCount": 0
              },
              "changed": false
            },
            {
              "before": {
                "href": "https://zhjg.scjdglj.gxzf.gov.cn:9087/icpsp-web-pc/name-register.html#/guide/base?busiType=07&entType=1100&marPrId=&marUniscId=",
                "hash": "#/guide/base?busiType=07&entType=1100&marPrId=&marUniscId=",
                "hasGuideBase": true,
                "hasCore": false,
                "hasYunbangban": false,
                "hasNamePrompt": false,
                "hasQualificationPrompt": false,
                "buttons": [
                  {
                    "text": "下一步",
                    "disabled": true
                  }
                ],
                "reqCount": 0
              },
              "actions": {
                "check_qualification": {
                  "clicked": 0,
                  "cbCount": 0,
                  "radioCount": 0
                },
                "close": false,
                "confirm": false,
                "select_not_apply": {
                  "ok": true,
                  "hit": "未申请",
                  "text": "广西数字政务一体化平台 标准版  国际版  首页  全部服务  **裕  用户信"
                },
                "next": false
              },
              "after": {
                "href": "https://zhjg.scjdglj.gxzf.gov.cn:9087/icpsp-web-pc/name-register.html#/guide/base?busiType=07&entType=1100&marPrId=&marUniscId=",
                "hash": "#/guide/base?busiType=07&entType=1100&marPrId=&marUniscId=",
                "hasGuideBase": true,
                "hasCore": false,
                "hasYunbangban": false,
                "hasNamePrompt": false,
                "hasQualificationPrompt": false,
                "buttons": [
                  {
                    "text": "下一步",
                    "disabled": true
                  }
                ],
                "reqCount": 0
              },
              "changed": false
            },
            {
              "before": {
                "href": "https://zhjg.scjdglj.gxzf.gov.cn:9087/icpsp-web-pc/name-register.html#/guide/base?busiType=07&entType=1100&marPrId=&marUniscId=",
                "hash": "#/guide/base?busiType=07&entType=1100&marPrId=&marUniscId=",
                "hasGuideBase": true,
                "hasCore": false,
                "hasYunbangban": false,
                "hasNamePrompt": false,
                "hasQualificationPrompt": false,
                "buttons": [
                  {
                    "text": "下一步",
                    "disabled": true
                  }
                ],
                "reqCount": 0
              },
              "actions": {
                "check_qualification": {
                  "clicked": 0,
                  "cbCount": 0,
                  "radioCount": 0
                },
                "close": false,
                "confirm": false,
                "select_not_apply": {
                  "ok": true,
                  "hit": "未申请",
                  "text": "广西数字政务一体化平台 标准版  国际版  首页  全部服务  **裕  用户信"
                },
                "next": false
              },
              "after": {
                "href": "https://zhjg.scjdglj.gxzf.gov.cn:9087/icpsp-web-pc/name-register.html#/guide/base?busiType=07&entType=1100&marPrId=&marUniscId=",
                "hash": "#/guide/base?busiType=07&entType=1100&marPrId=&marUniscId=",
                "hasGuideBase": true,
                "hasCore": false,
                "hasYunbangban": false,
                "hasNamePrompt": false,
                "hasQualificationPrompt": false,
                "buttons": [
                  {
                    "text": "下一步",
                    "disabled": true
                  }
                ],
                "reqCount": 0
              },
              "changed": false
            }
          ],
          "result": "blocked_no_side_effect",
          "final": {
            "href": "https://zhjg.scjdglj.gxzf.gov.cn:9087/icpsp-web-pc/name-register.html#/guide/base?busiType=07&entType=1100&marPrId=&marUniscId=",
            "hash": "#/guide/base?busiType=07&entType=1100&marPrId=&marUniscId=",
            "hasGuideBase": true,
            "hasCore": false,
            "hasYunbangban": false,
            "hasNamePrompt": false,
            "hasQualificationPrompt": false,
            "buttons": [
              {
                "text": "下一步",
                "disabled": true
              }
            ],
            "reqCount": 0
          }
        },
        {
          "target": "https://zhjg.scjdglj.gxzf.gov.cn:9087/icpsp-web-pc/name-register.html#/guide/base?busiType=07&entType=1100&marPrId=&marUniscId=",
          "logs": [
            {
              "before": {
                "href": "https://zhjg.scjdglj.gxzf.gov.cn:9087/icpsp-web-pc/name-register.html#/guide/base?busiType=07&entType=1100&marPrId=&marUniscId=",
                "hash": "#/guide/base?busiType=07&entType=1100&marPrId=&marUniscId=",
                "hasGuideBase": true,
                "hasCore": false,
                "hasYunbangban": false,
                "hasNamePrompt": false,
                "hasQualificationPrompt": false,
                "buttons": [
                  {
                    "text": "下一步",
                    "disabled": true
                  }
                ],
                "reqCount": 0
              },
              "actions": {
                "check_qualification": {
                  "clicked": 0,
                  "cbCount": 0,
                  "radioCount": 0
                },
                "close": false,
                "confirm": false,
                "select_not_apply": {
                  "ok": true,
                  "hit": "未申请",
                  "text": "广西数字政务一体化平台 标准版  国际版  首页  全部服务  **裕  用户信"
                },
                "next": false
              },
              "after": {
                "href": "https://zhjg.scjdglj.gxzf.gov.cn:9087/icpsp-web-pc/name-register.html#/guide/base?busiType=07&entType=1100&marPrId=&marUniscId=",
                "hash": "#/guide/base?busiType=07&entType=1100&marPrId=&marUniscId=",
                "hasGuideBase": true,
                "hasCore": false,
                "hasYunbangban": false,
                "hasNamePrompt": false,
                "hasQualificationPrompt": false,
                "buttons": [
                  {
                    "text": "下一步",
                    "disabled": true
                  }
                ],
                "reqCount": 0
              },
              "changed": false
            },
            {
              "before": {
                "href": "https://zhjg.scjdglj.gxzf.gov.cn:9087/icpsp-web-pc/name-register.html#/guide/base?busiType=07&entType=1100&marPrId=&marUniscId=",
                "hash": "#/guide/base?busiType=07&entType=1100&marPrId=&marUniscId=",
                "hasGuideBase": true,
                "hasCore": false,
                "hasYunbangban": false,
                "hasNamePrompt": false,
                "hasQualificationPrompt": false,
                "buttons": [
                  {
                    "text": "下一步",
                    "disabled": true
                  }
                ],
                "reqCount": 0
              },
              "actions": {
                "check_qualification": {
                  "clicked": 0,
                  "cbCount": 0,
                  "radioCount": 0
                },
                "close": false,
                "confirm": false,
                "select_not_apply": {
                  "ok": true,
                  "hit": "未申请",
                  "text": "广西数字政务一体化平台 标准版  国际版  首页  全部服务  **裕  用户信"
                },
                "next": false
              },
              "after": {
                "href": "https://zhjg.scjdglj.gxzf.gov.cn:9087/icpsp-web-pc/name-register.html#/guide/base?busiType=07&entType=1100&marPrId=&marUniscId=",
                "hash": "#/guide/base?busiType=07&entType=1100&marPrId=&marUniscId=",
                "hasGuideBase": true,
                "hasCore": false,
                "hasYunbangban": false,
                "hasNamePrompt": false,
                "hasQualificationPrompt": false,
                "buttons": [
                  {
                    "text": "下一步",
                    "disabled": true
                  }
                ],
                "reqCount": 0
              },
              "changed": false
            },
            {
              "before": {
                "href": "https://zhjg.scjdglj.gxzf.gov.cn:9087/icpsp-web-pc/name-register.html#/guide/base?busiType=07&entType=1100&marPrId=&marUniscId=",
                "hash": "#/guide/base?busiType=07&entType=1100&marPrId=&marUniscId=",
                "hasGuideBase": true,
                "hasCore": false,
                "hasYunbangban": false,
                "hasNamePrompt": false,
                "hasQualificationPrompt": false,
                "buttons": [
                  {
                    "text": "下一步",
                    "disabled": true
                  }
                ],
                "reqCount": 0
              },
              "actions": {
                "check_qualification": {
                  "clicked": 0,
                  "cbCount": 0,
                  "radioCount": 0
                },
                "close": false,
                "confirm": false,
                "select_not_apply": {
                  "ok": true,
                  "hit": "未申请",
                  "text": "广西数字政务一体化平台 标准版  国际版  首页  全部服务  **裕  用户信"
                },
                "next": false
              },
              "after": {
                "href": "https://zhjg.scjdglj.gxzf.gov.cn:9087/icpsp-web-pc/name-register.html#/guide/base?busiType=07&entType=1100&marPrId=&marUniscId=",
                "hash": "#/guide/base?busiType=07&entType=1100&marPrId=&marUniscId=",
                "hasGuideBase": true,
                "hasCore": false,
                "hasYunbangban": false,
                "hasNamePrompt": false,
                "hasQualificationPrompt": false,
                "buttons": [
                  {
                    "text": "下一步",
                    "disabled": true
                  }
                ],
                "reqCount": 0
              },
              "changed": false
            },
            {
              "before": {
                "href": "https://zhjg.scjdglj.gxzf.gov.cn:9087/icpsp-web-pc/name-register.html#/guide/base?busiType=07&entType=1100&marPrId=&marUniscId=",
                "hash": "#/guide/base?busiType=07&entType=1100&marPrId=&marUniscId=",
                "hasGuideBase": true,
                "hasCore": false,
                "hasYunbangban": false,
                "hasNamePrompt": false,
                "hasQualificationPrompt": false,
                "buttons": [
                  {
                    "text": "下一步",
                    "disabled": true
                  }
                ],
                "reqCount": 0
              },
              "actions": {
                "check_qualification": {
                  "clicked": 0,
                  "cbCount": 0,
                  "radioCount": 0
                },
                "close": false,
                "confirm": false,
                "select_not_apply": {
                  "ok": true,
                  "hit": "未申请",
                  "text": "广西数字政务一体化平台 标准版  国际版  首页  全部服务  **裕  用户信"
                },
                "next": false
              },
              "after": {
                "href": "https://zhjg.scjdglj.gxzf.gov.cn:9087/icpsp-web-pc/name-register.html#/guide/base?busiType=07&entType=1100&marPrId=&marUniscId=",
                "hash": "#/guide/base?busiType=07&entType=1100&marPrId=&marUniscId=",
                "hasGuideBase": true,
                "hasCore": false,
                "hasYunbangban": false,
                "hasNamePrompt": false,
                "hasQualificationPrompt": false,
                "buttons": [
                  {
                    "text": "下一步",
                    "disabled": true
                  }
                ],
                "reqCount": 0
              },
              "changed": false
            },
            {
              "before": {
                "href": "https://zhjg.scjdglj.gxzf.gov.cn:9087/icpsp-web-pc/name-register.html#/guide/base?busiType=07&entType=1100&marPrId=&marUniscId=",
                "hash": "#/guide/base?busiType=07&entType=1100&marPrId=&marUniscId=",
                "hasGuideBase": true,
                "hasCore": false,
                "hasYunbangban": false,
                "hasNamePrompt": false,
                "hasQualificationPrompt": false,
                "buttons": [
                  {
                    "text": "下一步",
                    "disabled": true
                  }
                ],
                "reqCount": 0
              },
              "actions": {
                "check_qualification": {
                  "clicked": 0,
                  "cbCount": 0,
                  "radioCount": 0
                },
                "close": false,
                "confirm": false,
                "select_not_apply": {
                  "ok": true,
                  "hit": "未申请",
                  "text": "广西数字政务一体化平台 标准版  国际版  首页  全部服务  **裕  用户信"
                },
                "next": false
              },
              "after": {
                "href": "https://zhjg.scjdglj.gxzf.gov.cn:9087/icpsp-web-pc/name-register.html#/guide/base?busiType=07&entType=1100&marPrId=&marUniscId=",
                "hash": "#/guide/base?busiType=07&entType=1100&marPrId=&marUniscId=",
                "hasGuideBase": true,
                "hasCore": false,
                "hasYunbangban": false,
                "hasNamePrompt": false,
                "hasQualificationPrompt": false,
                "buttons": [
                  {
                    "text": "下一步",
                    "disabled": true
                  }
                ],
                "reqCount": 0
              },
              "changed": false
            },
            {
              "before": {
                "href": "https://zhjg.scjdglj.gxzf.gov.cn:9087/icpsp-web-pc/name-register.html#/guide/base?busiType=07&entType=1100&marPrId=&marUniscId=",
                "hash": "#/guide/base?busiType=07&entType=1100&marPrId=&marUniscId=",
                "hasGuideBase": true,
                "hasCore": false,
                "hasYunbangban": false,
                "hasNamePrompt": false,
                "hasQualificationPrompt": false,
                "buttons": [
                  {
                    "text": "下一步",
                    "disabled": true
                  }
                ],
                "reqCount": 0
              },
              "actions": {
                "check_qualification": {
                  "clicked": 0,
                  "cbCount": 0,
                  "radioCount": 0
                },
                "close": false,
                "confirm": false,
                "select_not_apply": {
                  "ok": true,
                  "hit": "未申请",
                  "text": "广西数字政务一体化平台 标准版  国际版  首页  全部服务  **裕  用户信"
                },
                "next": false
              },
              "after": {
                "href": "https://zhjg.scjdglj.gxzf.gov.cn:9087/icpsp-web-pc/name-register.html#/guide/base?busiType=07&entType=1100&marPrId=&marUniscId=",
                "hash": "#/guide/base?busiType=07&entType=1100&marPrId=&marUniscId=",
                "hasGuideBase": true,
                "hasCore": false,
                "hasYunbangban": false,
                "hasNamePrompt": false,
                "hasQualificationPrompt": false,
                "buttons": [
                  {
                    "text": "下一步",
                    "disabled": true
                  }
                ],
                "reqCount": 0
              },
              "changed": false
            }
          ],
          "result": "blocked_no_side_effect",
          "final": {
            "href": "https://zhjg.scjdglj.gxzf.gov.cn:9087/icpsp-web-pc/name-register.html#/guide/base?busiType=07&entType=1100&marPrId=&marUniscId=",
            "hash": "#/guide/base?busiType=07&entType=1100&marPrId=&marUniscId=",
            "hasGuideBase": true,
            "hasCore": false,
            "hasYunbangban": false,
            "hasNamePrompt": false,
            "hasQualificationPrompt": false,
            "buttons": [
              {
                "text": "下一步",
                "disabled": true
              }
            ],
            "reqCount": 0
          }
        }
      ],
      "summary": {
        "any_transition": false,
        "all_blocked": true
      }
    }
  ],
  "environment": {
    "pages": [
      "https://zhjg.scjdglj.gxzf.gov.cn:9087/icpsp-web-pc/name-register.html#/guide/base?busiType=02_4&entType=4540&marPrId=&marUniscId="
    ],
    "has_icpsp_page": true
  },
  "ended_at": "2026-04-15 14:08:32"
}