{
  "code": "00000",
  "data": {
    "resultType": "0",
    "msg": "",
    "busiData": [
      {
        "hyCode": "C3053",
        "saveHyCode": "3053",
        "hyPecul": "玻璃仪器",
        "hyTypeName": "玻璃仪器制造",
        "enHyTypeName": null,
        "explains": "指实验室、医疗卫生用各种玻璃仪器和玻璃器皿以及玻璃管的制造。",
        "includesTitle": "包括对下列玻璃仪器的制造活动：",
        "includes": "玻璃计、量器：玻璃量筒，玻璃量杯，玻璃滴定管，玻璃吸量管，玻璃温度计，其他玻璃计、量器；石英玻璃制仪器和器皿：石英玻璃器皿坩埚、石英玻璃烧瓶、石英玻璃烧杯、石英玻璃蒸发皿、液位计用透明石英玻璃管、其他石英玻璃制仪器和器皿；耐热玻璃制仪器和器皿：玻璃烧器类器皿、玻璃蒸馏类器皿、玻璃蒸发类器皿、其他耐热玻璃制仪器和器皿；其他玻璃仪器及实验、医疗用玻璃器皿。",
        "unIncludes": "不包括：石英玻璃仪器及器皿制造，列入3051（技术玻璃制品制造）；药用瓶盖、瓶塞等用品，按其原料分别列入2039（软木制品及其他木制品制造）、2915（日用及医用橡胶制品制造）、3333（金属包装容器及材料制造）。",
        "busiType": "01,02,03,08,21,23,28",
        "entType": "1000,2000,3000,4000,5000,6000,7000,8000,9000",
        "isCustomHy": "0",
        "isRecomm": "0"
      },
      {
        "hyCode": "C3053",
        "saveHyCode": "3053",
        "hyPecul": "玻璃仪器制造",
        "hyTypeName": "玻璃仪器制造",
        "enHyTypeName": null,
        "explains": "指实验室、医疗卫生用各种玻璃仪器和玻璃器皿以及玻璃管的制造。",
        "includesTitle": "包括对下列玻璃仪器的制造活动：",
        "includes": "玻璃计、量器：玻璃量筒，玻璃量杯，玻璃滴定管，玻璃吸量管，玻璃温度计，其他玻璃计、量器；石英玻璃制仪器和器皿：石英玻璃器皿坩埚、石英玻璃烧瓶、石英玻璃烧杯、石英玻璃蒸发皿、液位计用透明石英玻璃管、其他石英玻璃制仪器和器皿；耐热玻璃制仪器和器皿：玻璃烧器类器皿、玻璃蒸馏类器皿、玻璃蒸发类器皿、其他耐热玻璃制仪器和器皿；其他玻璃仪器及实验、医疗用玻璃器皿。",
        "unIncludes": "不包括：石英玻璃仪器及器皿制造，列入3051（技术玻璃制品制造）；药用瓶盖、瓶塞等用品，按其原料分别列入2039（软木制品及其他木制品制造）、2915（日用及医用橡胶制品制造）、3333（金属包装容器及材料制造）。",
        "busiType": "21,01,28,23,08,02,03",
        "entType": "1000,2000,3000,4000,5000,6000,7000,9600,9200,9100",
        "isCustomHy": "0",
        "isRecomm": "0"
      }
    ]
  },
  "msg": "操作成功",
  "page": null,
  "_meta": {
    "hyPecul": "玻璃仪器",
    "entType": "4540",
    "busiType": "01"
  }
}