{
  "code": "00000",
  "data": {
    "resultType": "0",
    "msg": "",
    "busiData": [
      {
        "hyCode": "C2459",
        "saveHyCode": "2459",
        "hyPecul": "玩具",
        "hyTypeName": "其他玩具制造",
        "enHyTypeName": null,
        "explains": null,
        "includesTitle": "包括下列其他玩具制造活动：",
        "includes": "仿真模型及其附件：无动力装置仿真车模及其附件、无动力装置仿真航模及其附件、无动力装置仿真船模及其附件、无动力装置仿真建筑套件及其附件、其他无动力装置仿真模型及其附件；木制玩具：木制拼插类玩具、木制积木类玩具、木制拖拉类玩具、木制幼教类玩具、其他木制玩具；玩具乐器；儿童娱乐塑形用膏、泥；毛绒玩具；纯布娃娃玩具；其他玩具。",
        "unIncludes": null,
        "busiType": "21,01,28,23,08,02,03",
        "entType": "1000,2000,3000,4000,5000,6000,7000,9600,9200,9100",
        "isCustomHy": "0",
        "isRecomm": "0"
      },
      {
        "hyCode": "C2456",
        "saveHyCode": "2456",
        "hyPecul": "玩具",
        "hyTypeName": "儿童乘骑玩耍的童车类产品制造",
        "enHyTypeName": null,
        "explains": "指制造供儿童乘骑玩耍的童车类产品（含儿童推车、婴儿学步车）。",
        "includesTitle": "包括下列儿童乘骑玩耍的童车类产品制造活动：",
        "includes": "供儿童乘骑带轮玩具：婴儿学步车、儿童自行车、儿童三轮车、儿童推车、电动童车、其他供儿童乘骑带轮玩具。",
        "unIncludes": "不包括：婴儿推车及其零件制造，列入4119（其他日用杂品制造）。",
        "busiType": "01,02,03,08,21,23,28",
        "entType": "1000,2000,3000,4000,5000,6000,7000,8000,9000",
        "isCustomHy": "0",
        "isRecomm": "0"
      },
      {
        "hyCode": "F5299",
        "saveHyCode": "5299",
        "hyPecul": "玩具",
        "hyTypeName": "其他未列明零售业",
        "enHyTypeName": null,
        "explains": null,
        "includesTitle": "包括下列其他未列明零售业活动：",
        "includes": "其他未列明零售服务。",
        "unIncludes": null,
        "busiType": "01,02,03,08,21,23,28",
        "entType": "1000,2000,3000,4000,5000,6000,7000,8000,9000",
        "isCustomHy": "0",
        "isRecomm": "0"
      },
      {
        "hyCode": "C2455",
        "saveHyCode": "2455",
        "hyPecul": "玩具",
        "hyTypeName": "娃娃玩具制造",
        "enHyTypeName": null,
        "explains": "指制造供14岁以下儿童玩耍的、至少头部和四肢由非纺织物材质的聚合材料制成，并带有服装或身体由软性材料填充的非电的婴儿娃娃或人物娃娃玩具产品。",
        "includesTitle": "包括下列娃娃玩具制造活动：",
        "includes": "塑胶、陶瓷、搪胶娃娃；公仔；其他娃娃玩具。",
        "unIncludes": "不包括：毛绒玩具，列入2459（其他玩具制造）；纯布娃娃玩具，列入2459（其他玩具制造）。",
        "busiType": "01,02,03,08,21,23,28",
        "entType": "1000,2000,3000,4000,5000,6000,7000,8000,9000",
        "isCustomHy": "0",
        "isRecomm": "0"
      },
      {
        "hyCode": "C2454",
        "saveHyCode": "2454",
        "hyPecul": "玩具",
        "hyTypeName": "弹射玩具制造",
        "enHyTypeName": null,
        "explains": null,
        "includesTitle": "包括下列弹射玩具制造活动：",
        "includes": "弹射玩具：玩具弓箭、玩具飞镖、玩具弹射枪等。",
        "unIncludes": null,
        "busiType": "01,02,03,08,21,23,28",
        "entType": "1000,2000,3000,4000,5000,6000,7000,8000,9000",
        "isCustomHy": "0",
        "isRecomm": "0"
      },
      {
        "hyCode": "C2453",
        "saveHyCode": "2453",
        "hyPecul": "玩具",
        "hyTypeName": "金属玩具制造",
        "enHyTypeName": null,
        "explains": "指制造供14岁以下儿童玩耍的、玩具主体或主要玩耍部分由金属材料制成的，非预定承载儿童体重的非电玩具产品。",
        "includesTitle": "包括下列金属玩具制造活动：",
        "includes": "金属玩具车、飞机（非电动）；金属玩具枪；金属模型（非电动）：模型汽车、模型飞机、模型火车等；其他金属玩具（非电动）。",
        "unIncludes": null,
        "busiType": "01,02,03,08,21,23,28",
        "entType": "1000,2000,3000,4000,5000,6000,7000,8000,9000",
        "isCustomHy": "0",
        "isRecomm": "0"
      },
      {
        "hyCode": "C2452",
        "saveHyCode": "2452",
        "hyPecul": "玩具",
        "hyTypeName": "塑胶玩具制造",
        "enHyTypeName": null,
        "explains": "指制造供14岁以下儿童玩耍的、玩具主体或主要玩耍部分由塑胶制成的，非预定承载儿童体重的非电玩具产品。",
        "includesTitle": "包括下列塑胶玩具制造活动：",
        "includes": "塑胶玩具：静态塑胶玩具、机动塑胶玩具、其他塑胶玩具、塑胶（仿真）模型（无动力）。",
        "unIncludes": "不包括：婴儿推车及其零件制造，列入4119（其他日用杂品制造）。",
        "busiType": "01,02,03,08,21,23,28",
        "entType": "1000,2000,3000,4000,5000,6000,7000,8000,9000",
        "isCustomHy": "0",
        "isRecomm": "0"
      },
      {
        "hyCode": "C2451",
        "saveHyCode": "2451",
        "hyPecul": "玩具",
        "hyTypeName": "电玩具制造",
        "enHyTypeName": null,
        "explains": "指制造供14岁以下儿童玩耍的、至少有一种玩耍功能需要使用额定电压小于或等于24V的玩具产品。",
        "includesTitle": "包括下列电玩具制造活动：",
        "includes": "带动力装置仿真模型及其附件：带动力装置仿真车模及其附件、带动力装置仿真航模及其附件、带动力装置仿真船模及其附件、其他带动力装置仿真模型及其附件。",
        "unIncludes": "不包括：婴儿推车及其零件制造，列入4119（其他日用杂品制造）。",
        "busiType": "01,02,03,08,21,23,28",
        "entType": "1000,2000,3000,4000,5000,6000,7000,8000,9000",
        "isCustomHy": "0",
        "isRecomm": "0"
      },
      {
        "hyCode": "F5149",
        "saveHyCode": "5149",
        "hyPecul": "儿童玩具",
        "hyTypeName": "其他文化用品批发",
        "enHyTypeName": null,
        "explains": null,
        "includesTitle": "包括下列其他文化用品批发活动：",
        "includes": "玩具批发服务（木制玩具批发服务，拼插、变形玩具批发服务，仿真模型玩具批发服务，布绒玩具批发服务，电动玩具批发服务，遥控玩具批发服务，益智玩具批发服务，婴儿玩具批发服务，其他玩具批发服务）、游艺及娱乐用品批发服务（电子游戏机批发服务、弹子游戏器材批发服务、台球器材批发服务、飞镖器材批发服务、沙狐球器材批发服务、小魔术用品批发服务、其他游艺及娱乐用品批发服务）、照相器材批发服务（照相机批发服务，照相辅助器材批发服务，胶卷、相纸批发服务，冲印药剂批发服务，家用冲印设备批发服务，其他照相器材批发服务）、其他文化娱乐用品批发服务（望远镜批发服务、动漫衍生产品批发服务、其他未列明文化娱乐用品批发服务）；玩具批发和进出口：木制玩具、拼插玩具、变形玩具、仿真模型玩具、布绒玩具、电动玩具、遥控玩具、益智玩具、婴儿玩具及其他玩具批发和进出口；游艺及娱乐用品批发和进出口：电子游戏机、弹子游戏器材、台球器材、飞镖器材、砂壶球器材、小魔术用品及其他室内娱乐用品批发和进出口；照相器材批发和进出口：照相机、照相辅助器材、胶卷、相纸、冲印药剂、家用冲印设备及其他照相器材批发和进出口；其他文化娱乐用品批发和进出口：望远镜批发和进出口和其他未列明文化娱乐用品批发和进出口。",
        "unIncludes": "不包括：大型照相冲洗、扩印设备的批发和进出口，列入5179（其他机械设备及电子产品批发）；大型露天娱乐设备的批发和进出口，列入5179（其他机械设备及电子产品批发）。",
        "busiType": "21,01,28,23,08,02,03",
        "entType": "1000,2000,3000,4000,5000,6000,7000,9600,9200,9100",
        "isCustomHy": "0",
        "isRecomm": "0"
      },
      {
        "hyCode": "C2459",
        "saveHyCode": "2459",
        "hyPecul": "玩具制造",
        "hyTypeName": "其他玩具制造",
        "enHyTypeName": null,
        "explains": null,
        "includesTitle": "包括下列其他玩具制造活动：",
        "includes": "仿真模型及其附件：无动力装置仿真车模及其附件、无动力装置仿真航模及其附件、无动力装置仿真船模及其附件、无动力装置仿真建筑套件及其附件、其他无动力装置仿真模型及其附件；木制玩具：木制拼插类玩具、木制积木类玩具、木制拖拉类玩具、木制幼教类玩具、其他木制玩具；玩具乐器；儿童娱乐塑形用膏、泥；毛绒玩具；纯布娃娃玩具；其他玩具。",
        "unIncludes": null,
        "busiType": "21,01,28,23,08,02,03",
        "entType": "1000,2000,3000,4000,5000,6000,7000,9600,9200,9100",
        "isCustomHy": "0",
        "isRecomm": "0"
      },
      {
        "hyCode": "C2459",
        "saveHyCode": "2459",
        "hyPecul": "玩具加工",
        "hyTypeName": "其他玩具制造",
        "enHyTypeName": null,
        "explains": null,
        "includesTitle": "包括下列其他玩具制造活动：",
        "includes": "仿真模型及其附件：无动力装置仿真车模及其附件、无动力装置仿真航模及其附件、无动力装置仿真船模及其附件、无动力装置仿真建筑套件及其附件、其他无动力装置仿真模型及其附件；木制玩具：木制拼插类玩具、木制积木类玩具、木制拖拉类玩具、木制幼教类玩具、其他木制玩具；玩具乐器；儿童娱乐塑形用膏、泥；毛绒玩具；纯布娃娃玩具；其他玩具。",
        "unIncludes": null,
        "busiType": "21,01,28,23,08,02,03",
        "entType": "1000,2000,3000,4000,5000,6000,7000,9600,9200,9100",
        "isCustomHy": "0",
        "isRecomm": "0"
      },
      {
        "hyCode": "C2459",
        "saveHyCode": "2459",
        "hyPecul": "玩具模型",
        "hyTypeName": "其他玩具制造",
        "enHyTypeName": null,
        "explains": null,
        "includesTitle": "包括下列其他玩具制造活动：",
        "includes": "仿真模型及其附件：无动力装置仿真车模及其附件、无动力装置仿真航模及其附件、无动力装置仿真船模及其附件、无动力装置仿真建筑套件及其附件、其他无动力装置仿真模型及其附件；木制玩具：木制拼插类玩具、木制积木类玩具、木制拖拉类玩具、木制幼教类玩具、其他木制玩具；玩具乐器；儿童娱乐塑形用膏、泥；毛绒玩具；纯布娃娃玩具；其他玩具。",
        "unIncludes": null,
        "busiType": "21,01,28,23,08,02,03",
        "entType": "1000,2000,3000,4000,5000,6000,7000,9600,9200,9100",
        "isCustomHy": "0",
        "isRecomm": "0"
      },
      {
        "hyCode": "F5149",
        "saveHyCode": "5149",
        "hyPecul": "玩具销售",
        "hyTypeName": "其他文化用品批发",
        "enHyTypeName": null,
        "explains": null,
        "includesTitle": "包括下列其他文化用品批发活动：",
        "includes": "玩具批发服务（木制玩具批发服务，拼插、变形玩具批发服务，仿真模型玩具批发服务，布绒玩具批发服务，电动玩具批发服务，遥控玩具批发服务，益智玩具批发服务，婴儿玩具批发服务，其他玩具批发服务）、游艺及娱乐用品批发服务（电子游戏机批发服务、弹子游戏器材批发服务、台球器材批发服务、飞镖器材批发服务、沙狐球器材批发服务、小魔术用品批发服务、其他游艺及娱乐用品批发服务）、照相器材批发服务（照相机批发服务，照相辅助器材批发服务，胶卷、相纸批发服务，冲印药剂批发服务，家用冲印设备批发服务，其他照相器材批发服务）、其他文化娱乐用品批发服务（望远镜批发服务、动漫衍生产品批发服务、其他未列明文化娱乐用品批发服务）；玩具批发和进出口：木制玩具、拼插玩具、变形玩具、仿真模型玩具、布绒玩具、电动玩具、遥控玩具、益智玩具、婴儿玩具及其他玩具批发和进出口；游艺及娱乐用品批发和进出口：电子游戏机、弹子游戏器材、台球器材、飞镖器材、砂壶球器材、小魔术用品及其他室内娱乐用品批发和进出口；照相器材批发和进出口：照相机、照相辅助器材、胶卷、相纸、冲印药剂、家用冲印设备及其他照相器材批发和进出口；其他文化娱乐用品批发和进出口：望远镜批发和进出口和其他未列明文化娱乐用品批发和进出口。",
        "unIncludes": "不包括：大型照相冲洗、扩印设备的批发和进出口，列入5179（其他机械设备及电子产品批发）；大型露天娱乐设备的批发和进出口，列入5179（其他机械设备及电子产品批发）。",
        "busiType": "21,01,28,23,08,02,03",
        "entType": "1000,2000,3000,4000,5000,6000,7000,9600,9200,9100",
        "isCustomHy": "0",
        "isRecomm": "0"
      },
      {
        "hyCode": "C2451",
        "saveHyCode": "2451",
        "hyPecul": "电玩具制造",
        "hyTypeName": "电玩具制造",
        "enHyTypeName": null,
        "explains": "指制造供14岁以下儿童玩耍的、至少有一种玩耍功能需要使用额定电压小于或等于24V的玩具产品。",
        "includesTitle": "包括下列电玩具制造活动：",
        "includes": "带动力装置仿真模型及其附件：带动力装置仿真车模及其附件、带动力装置仿真航模及其附件、带动力装置仿真船模及其附件、其他带动力装置仿真模型及其附件。",
        "unIncludes": "不包括：婴儿推车及其零件制造，列入4119（其他日用杂品制造）。",
        "busiType": "21,01,28,23,08,02,03",
        "entType": "1000,2000,3000,4000,5000,6000,7000,9600,9200,9100",
        "isCustomHy": "0",
        "isRecomm": "0"
      },
      {
        "hyCode": "C2452",
        "saveHyCode": "2452",
        "hyPecul": "塑胶玩具制造",
        "hyTypeName": "塑胶玩具制造",
        "enHyTypeName": null,
        "explains": "指制造供14岁以下儿童玩耍的、玩具主体或主要玩耍部分由塑胶制成的，非预定承载儿童体重的非电玩具产品。",
        "includesTitle": "包括下列塑胶玩具制造活动：",
        "includes": "塑胶玩具：静态塑胶玩具、机动塑胶玩具、其他塑胶玩具、塑胶（仿真）模型（无动力）。",
        "unIncludes": "不包括：婴儿推车及其零件制造，列入4119（其他日用杂品制造）。",
        "busiType": "21,01,28,23,08,02,03",
        "entType": "1000,2000,3000,4000,5000,6000,7000,9600,9200,9100",
        "isCustomHy": "0",
        "isRecomm": "0"
      },
      {
        "hyCode": "C2455",
        "saveHyCode": "2455",
        "hyPecul": "娃娃玩具制造",
        "hyTypeName": "娃娃玩具制造",
        "enHyTypeName": null,
        "explains": "指制造供14岁以下儿童玩耍的、至少头部和四肢由非纺织物材质的聚合材料制成，并带有服装或身体由软性材料填充的非电的婴儿娃娃或人物娃娃玩具产品。",
        "includesTitle": "包括下列娃娃玩具制造活动：",
        "includes": "塑胶、陶瓷、搪胶娃娃；公仔；其他娃娃玩具。",
        "unIncludes": "不包括：毛绒玩具，列入2459（其他玩具制造）；纯布娃娃玩具，列入2459（其他玩具制造）。",
        "busiType": "21,01,28,23,08,02,03",
        "entType": "1000,2000,3000,4000,5000,6000,7000,9600,9200,9100",
        "isCustomHy": "0",
        "isRecomm": "0"
      },
      {
        "hyCode": "C2454",
        "saveHyCode": "2454",
        "hyPecul": "弹射玩具制造",
        "hyTypeName": "弹射玩具制造",
        "enHyTypeName": null,
        "explains": null,
        "includesTitle": "包括下列弹射玩具制造活动：",
        "includes": "弹射玩具：玩具弓箭、玩具飞镖、玩具弹射枪等。",
        "unIncludes": null,
        "busiType": "21,01,28,23,08,02,03",
        "entType": "1000,2000,3000,4000,5000,6000,7000,9600,9200,9100",
        "isCustomHy": "0",
        "isRecomm": "0"
      },
      {
        "hyCode": "C2453",
        "saveHyCode": "2453",
        "hyPecul": "金属玩具制造",
        "hyTypeName": "金属玩具制造",
        "enHyTypeName": null,
        "explains": "指制造供14岁以下儿童玩耍的、玩具主体或主要玩耍部分由金属材料制成的，非预定承载儿童体重的非电玩具产品。",
        "includesTitle": "包括下列金属玩具制造活动：",
        "includes": "金属玩具车、飞机（非电动）；金属玩具枪；金属模型（非电动）：模型汽车、模型飞机、模型火车等；其他金属玩具（非电动）。",
        "unIncludes": null,
        "busiType": "21,01,28,23,08,02,03",
        "entType": "1000,2000,3000,4000,5000,6000,7000,9600,9200,9100",
        "isCustomHy": "0",
        "isRecomm": "0"
      }
    ]
  },
  "msg": "操作成功",
  "page": null,
  "_meta": {
    "hyPecul": "玩具",
    "entType": "1100",
    "busiType": "01"
  }
}